MANIFEST.in
README.md
setup.cfg
setup.py
docs/__init__.py
uqer/PortfolioConstruction.py
uqer/__init__.py
uqer/authorize.py
uqer/config.py
uqer/data.py
uqer/factor.py
uqer/notebook.py
uqer/trading.py
uqer/upgrade.py
uqer/uqer.py
uqer/user_factor.py
uqer/utils.py
uqer/version.py
uqer.egg-info/PKG-INFO
uqer.egg-info/SOURCES.txt
uqer.egg-info/dependency_links.txt
uqer.egg-info/top_level.txt
uqer/DataAPI/ACMR.py
uqer/DataAPI/CCXE.py
uqer/DataAPI/CHINABOND.py
uqer/DataAPI/CSI.py
uqer/DataAPI/DATAYES.py
uqer/DataAPI/DYZH.py
uqer/DataAPI/DataCube.py
uqer/DataAPI/FDC.py
uqer/DataAPI/FH.py
uqer/DataAPI/GG.py
uqer/DataAPI/IT.py
uqer/DataAPI/IVOLATILITY.py
uqer/DataAPI/JDW.py
uqer/DataAPI/JL.py
uqer/DataAPI/JY.py
uqer/DataAPI/JYDB.py
uqer/DataAPI/KGRAPH.py
uqer/DataAPI/NH.py
uqer/DataAPI/OTHER.py
uqer/DataAPI/QAI.py
uqer/DataAPI/QGW.py
uqer/DataAPI/SILKRIVER.py
uqer/DataAPI/SW.py
uqer/DataAPI/TEJ.py
uqer/DataAPI/__init__.py
uqer/DataAPI/api_base.py
uqer/DataAPI/settings.py
uqer/DataAPI/version.py
uqer/SignalAnalysis/__init__.py
uqer/SignalAnalysis/const.py
uqer/SignalAnalysis/signal_utils.py
uqer/SignalAnalysis/tears.py
uqer/mfclient/__init__.py
uqer/mfclient/portfolio_construct.py
uqer/mfclient/signal_process.py
uqer/mfclient/signal_process_check.py