Metadata-Version: 1.2
Name: uqer
Version: 1.3.39
Summary: Package for DataYes Uqer API access
Home-page: UNKNOWN
Author: uqer
Author-email: service.uqer@datayes.com
Maintainer: uqer
Maintainer-email: service.uqer@datayes.com
License: DataYes
Platform: UNKNOWN
